L0_Smoothing/__init__.py
L0_Smoothing/cli.py
L0_Smoothing/normal/L0_Smoothing.py
L0_Smoothing/normal/__init__.py
L0_Smoothing/normal/psf2otf.py
L0_Smoothing/pyocl/GCArray.py
L0_Smoothing/pyocl/L0_Smoothing.py
L0_Smoothing/pyocl/__init__.py
L0_Smoothing/pyocl/gen_size_table.py
L0_Smoothing/pyocl/get_size.py
L0_Smoothing/pyocl/matlab_utils.py
L0_Smoothing/pyocl/ocl_func/__init__.py
L0_Smoothing/pyocl/ocl_func/circshift2D.cl
L0_Smoothing/pyocl/ocl_func/circshift2D.py
L0_Smoothing/pyocl/ocl_func/cl_function.py
L0_Smoothing/pyocl/ocl_func/crop2D.cl
L0_Smoothing/pyocl/ocl_func/crop2D.py
L0_Smoothing/pyocl/ocl_func/fancyindex2D.cl
L0_Smoothing/pyocl/ocl_func/fancyindex2D.py
L0_Smoothing/pyocl/ocl_func/pad2D_constant.cl
L0_Smoothing/pyocl/ocl_func/pad2D_constant.py
L0_Smoothing-0.1.3.dist-info/METADATA
L0_Smoothing-0.1.3.dist-info/WHEEL
L0_Smoothing-0.1.3.dist-info/entry_points.txt
L0_Smoothing-0.1.3.dist-info/top_level.txt
L0_Smoothing-0.1.3.dist-info/RECORD
