Metadata-Version: 2.1
Name: L0-Smoothing
Version: 0.1.3
Summary: Implementation of 《Image Smoothing via L0 Gradient Minimization》
Home-page: https://github.com/TsXor/L0-Smoothing
Author: Nrupatunga(normal), TsXor(pyocl)
Author-email: nrupatunga.s@byjus.com, zhang050525@qq.com
License: MIT
Classifier: Programming Language :: Python :: 3
Classifier: License :: OSI Approved :: MIT License
Classifier: Operating System :: OS Independent
Classifier: Topic :: Scientific/Engineering :: Image Processing
Classifier: Environment :: GPU
Requires-Python: >=3
Requires-Dist: numpy
Requires-Dist: opencv-python
Requires-Dist: pyopencl
Requires-Dist: pyvkfft
